[
{"cat" : "Session","pid" :213556,"tid" :213556,"dur" :107,"ts" :3,"ph" : "X","name" :"model_loading_uri","args" : {}},
{"cat" : "Session","pid" :213556,"tid" :213556,"dur" :355,"ts" :131,"ph" : "X","name" :"session_initialization","args" : {}},
{"cat" : "Node","pid" :213556,"tid" :213556,"dur" :0,"ts" :553,"ph" : "X","name" :"AveragePool_0_fence_before","args" : {"op_name" : "AveragePool"}},
{"cat" : "Node","pid" :213556,"tid" :213556,"dur" :46,"ts" :559,"ph" : "X","name" :"AveragePool_0_kernel_time","args" : {"thread_scheduling_stats" : {"main_thread": {"thread_pool_name": "session-6-intra-op", "thread_id": "47317700232704", "block_size": [], "core": -1, "Distribution": 0, "DistributionEnqueue": 0, "Run": 0, "Wait": 0, "WaitRevoke": 0}, "sub_threads": {"47318104045312": {"num_run": 0, "core": -1},"thread::id of a non-executing thread": {"num_run": 0, "core": -1},"thread::id of a non-executing thread": {"num_run": 0, "core": -1},"thread::id of a non-executing thread": {"num_run": 0, "core": -1},"thread::id of a non-executing thread": {"num_run": 0, "core": -1},"thread::id of a non-executing thread": {"num_run": 0, "core": -1},"thread::id of a non-executing thread": {"num_run": 0, "core": -1},"thread::id of a non-executing thread": {"num_run": 0, "core": -1},"thread::id of a non-executing thread": {"num_run": 0, "core": -1},"thread::id of a non-executing thread": {"num_run": 0, "core": -1},"thread::id of a non-executing thread": {"num_run": 0, "core": -1},"thread::id of a non-executing thread": {"num_run": 0, "core": -1},"thread::id of a non-executing thread": {"num_run": 0, "core": -1},"thread::id of a non-executing thread": {"num_run": 0, "core": -1},"thread::id of a non-executing thread": {"num_run": 0, "core": -1},"thread::id of a non-executing thread": {"num_run": 0, "core": -1},"thread::id of a non-executing thread": {"num_run": 0, "core": -1},"thread::id of a non-executing thread": {"num_run": 0, "core": -1},"thread::id of a non-executing thread": {"num_run": 0, "core": -1},"thread::id of a non-executing thread": {"num_run": 0, "core": -1},"thread::id of a non-executing thread": {"num_run": 0, "core": -1},"thread::id of a non-executing thread": {"num_run": 0, "core": -1},"thread::id of a non-executing thread": {"num_run": 0, "core": -1},"thread::id of a non-executing thread": {"num_run": 0, "core": -1},"thread::id of a non-executing thread": {"num_run": 0, "core": -1},"thread::id of a non-executing thread": {"num_run": 0, "core": -1},"thread::id of a non-executing thread": {"num_run": 0, "core": -1},"thread::id of a non-executing thread": {"num_run": 0, "core": -1},"47318059919104": {"num_run": 0, "core": -1},"thread::id of a non-executing thread": {"num_run": 0, "core": -1},"thread::id of a non-executing thread": {"num_run": 0, "core": -1}}},"output_type_shape" : [{"float":[1,3,16,16]}],"output_size" : "3072","parameter_size" : "0","activation_size" : "12288","node_index" : "0","input_type_shape" : [{"float":[1,3,32,32]}],"provider" : "CPUExecutionProvider","op_name" : "AveragePool"}},
{"cat" : "Node","pid" :213556,"tid" :213556,"dur" :0,"ts" :609,"ph" : "X","name" :"AveragePool_0_fence_after","args" : {"op_name" : "AveragePool"}},
{"cat" : "Session","pid" :213556,"tid" :213556,"dur" :73,"ts" :545,"ph" : "X","name" :"SequentialExecutor::Execute","args" : {}},
{"cat" : "Session","pid" :213556,"tid" :213556,"dur" :91,"ts" :530,"ph" : "X","name" :"model_run","args" : {}}
]
